textual_plotext/__init__.py
textual_plotext/__main__.py
textual_plotext/plot.py
textual_plotext/plotext/__init__.py
textual_plotext/plotext/__init__.pyi
textual_plotext/plotext/_figure.py
textual_plotext/plotext/_figure.pyi
textual_plotext/plotext_plot.py
textual_plotext/py.typed
textual_plotext-1.0.0.dist-info/LICENSE
textual_plotext-1.0.0.dist-info/METADATA
textual_plotext-1.0.0.dist-info/WHEEL
textual_plotext-1.0.0.dist-info/RECORD
