Metadata-Version: 2.1
Name: textual-plotext
Version: 1.0.0
Summary: A Textual widget wrapper for the Plotext plotting library
Home-page: https://github.com/Textualize/textual-plotext
License: MIT
Author: Dave Pearson
Author-email: dave@textualize.io
Requires-Python: >=3.8.1,<4.0.0
Classifier: Development Status :: 4 - Beta
Classifier: Environment :: Console
Classifier: Intended Audience :: Developers
Classifier: License :: OSI Approved :: MIT License
Classifier: Operating System :: MacOS
Classifier: Operating System :: Microsoft :: Windows :: Windows 10
Classifier: Operating System :: Microsoft :: Windows :: Windows 11
Classifier: Operating System :: POSIX :: Linux
Classifier: Programming Language :: Python :: 3
Classifier: Programming Language :: Python :: 3.9
Classifier: Programming Language :: Python :: 3.10
Classifier: Programming Language :: Python :: 3.11
Classifier: Programming Language :: Python :: 3.12
Classifier: Programming Language :: Python :: 3.7
Classifier: Programming Language :: Python :: 3.8
Classifier: Topic :: Scientific/Engineering :: Visualization
Classifier: Typing :: Typed
Requires-Dist: plotext (>=5.2.8,<6.0.0)
Requires-Dist: textual (>=0.86.2,<0.87.0)
Project-URL: Bug Tracker, https://github.com/Textualize/textual-plotext/issues
Project-URL: Repository, https://github.com/Textualize/textual-plotext
